loggingsfactory/__init__.py
loggingsfactory/logging.py
loggingsfactory/constants/__init__.py
loggingsfactory/constants/config.py
loggingsfactory/constants/keys.py
loggingsfactory/helpers/__init__.py
loggingsfactory/helpers/decorators.py
loggingsfactory/helpers/formats.py
loggingsfactory/helpers/singletons.py
loggingsfactory/loggers/__init__.py
loggingsfactory/loggers/asyncelk.py
loggingsfactory/loggers/elk.py
loggingsfactory/loggers/interface.py
loggingsfactory/loggers/loguru.py
loggingsfactory-0.0.4.dist-info/LICENSE
loggingsfactory-0.0.4.dist-info/METADATA
loggingsfactory-0.0.4.dist-info/WHEEL
loggingsfactory-0.0.4.dist-info/top_level.txt
loggingsfactory-0.0.4.dist-info/RECORD
