Metadata-Version: 2.1
Name: loggingsfactory
Version: 0.0.4
Summary: A logging factory wrapper for loguru and elasticsearch
Home-page: https://github.com/reshinto/loggingsfactory
Author: Terence
Author-email: terence_kong2002@hotmail.com
License: UNKNOWN
Project-URL: Bug Tracker, https://github.com/reshinto/loggingsfactory/issues
Platform: UNKNOWN
Classifier: Programming Language :: Python :: 3
Classifier: License :: OSI Approved :: MIT License
Classifier: Operating System :: OS Independent
Requires-Python: >=3.6
License-File: LICENSE
Requires-Dist: elasticsearch[async] (==7.15.0)
Requires-Dist: elasticsearch-dbapi
Requires-Dist: loguru
Requires-Dist: pandas
Requires-Dist: aiohttp
